threefg15/__init__.py
threefg15/cli.py
threefg15/core.py
threefg15-1.0.1.dist-info/licenses/LICENSE
threefg15-1.0.1.dist-info/METADATA
threefg15-1.0.1.dist-info/WHEEL
threefg15-1.0.1.dist-info/entry_points.txt
threefg15-1.0.1.dist-info/top_level.txt
threefg15-1.0.1.dist-info/RECORD
