Metadata-Version: 2.4
Name: threefg15
Version: 1.0.1
Summary: Python driver and CLI for the OnRobot 3FG15 gripper via Modbus TCP/RTU
Author-email: Marcel Ochsendorf <info@marcelochsendorf.com>
License: MIT
Classifier: Programming Language :: Python :: 3
Classifier: License :: OSI Approved :: MIT License
Classifier: Operating System :: OS Independent
Requires-Python: >=3.8
License-File: LICENSE
Requires-Dist: pymodbus>=3.0.0
Requires-Dist: typer>=0.9.0
Dynamic: license-file
